BrainGB/__init__.py
BrainGB/dataset/__init__.py
BrainGB/dataset/base_transform.py
BrainGB/dataset/brain_data.py
BrainGB/dataset/brain_dataset.py
BrainGB/dataset/maskable_list.py
BrainGB/dataset/transforms.py
BrainGB/dataset/utils.py
BrainGB/dataset/abcd/__init__.py
BrainGB/dataset/abcd/load_abcd.py
BrainGB/models/__init__.py
BrainGB/models/brainnn.py
BrainGB/models/gat.py
BrainGB/models/gcn.py
BrainGB/models/losses.py
BrainGB/models/mlp.py
BrainGB/models/pna.py
BrainGB/utils/__init__.py
BrainGB/utils/bin_edges.py
BrainGB/utils/get_y.py
BrainGB/utils/mixup.py
BrainGB-1.0.4.dist-info/LICENSE
BrainGB-1.0.4.dist-info/METADATA
BrainGB-1.0.4.dist-info/WHEEL
BrainGB-1.0.4.dist-info/top_level.txt
BrainGB-1.0.4.dist-info/RECORD
