Metadata-Version: 2.1
Name: BrainGB
Version: 1.0.4
Summary: Emory Brain Benchmark package
Home-page: https://github.com/
Author: Emory Brain Network
Author-email: wdai26@emory.edu
Project-URL: Bug Tracker, https://github.com/
Classifier: Programming Language :: Python :: 3
Classifier: License :: OSI Approved :: MIT License
Classifier: Operating System :: OS Independent
Requires-Python: >=3.6
License-File: LICENSE
Requires-Dist: numpy (>=1.19.5)
Requires-Dist: torch (>=1.10.2)
Requires-Dist: scikit-learn (>=0.24.2)
Requires-Dist: networkx (>=2.5.1)
Requires-Dist: node2vec (>=0.4.3)
Requires-Dist: scipy
Requires-Dist: torch-geometric
Requires-Dist: torch-scatter
Requires-Dist: torch-sparse
Provides-Extra: brainnet
Requires-Dist: ReportLab (>=1.2) ; extra == 'brainnet'
Requires-Dist: RXP ; extra == 'brainnet'
